nxpprog/__init__.py
nxpprog/__main__.py
nxpprog/nxpprog.py
nxpprog-1.0.3.dist-info/LICENSE
nxpprog-1.0.3.dist-info/METADATA
nxpprog-1.0.3.dist-info/WHEEL
nxpprog-1.0.3.dist-info/entry_points.txt
nxpprog-1.0.3.dist-info/top_level.txt
nxpprog-1.0.3.dist-info/RECORD
