Metadata-Version: 2.1
Name: nxpprog
Version: 1.0.3
Summary: Programmer for NXP Microcontrollers using the NXP ISP protocol
Author-email: libhal organization <libembeddedhal@gmail.com>
Project-URL: Homepage, https://github.com/libhal/nxpprog
Project-URL: Bug Tracker, https://github.com/libhal/nxpprog/issues
Classifier: Programming Language :: Python :: 3
Classifier: License :: OSI Approved :: MIT License
Classifier: Operating System :: MacOS :: MacOS X
Classifier: Operating System :: POSIX :: Linux
Requires-Python: >=3.9
License-File: LICENSE
Requires-Dist: pyserial (>=3.4)
Requires-Dist: click (>=7.1.2)
Requires-Dist: rich (==12.6.0)
